cloudwatchlogger/__init__.py
cloudwatchlogger/cloudwatchlogger.py
cloudwatchlogger-0.2.dist-info/METADATA
cloudwatchlogger-0.2.dist-info/WHEEL
cloudwatchlogger-0.2.dist-info/top_level.txt
cloudwatchlogger-0.2.dist-info/RECORD
