Metadata-Version: 2.1
Name: cloudwatchlogger
Version: 0.2
Requires-Dist: boto3
